theus/__init__.py
theus/__main__.py
theus/audit.py
theus/cli.py
theus/config.py
theus/context.py
theus/contracts.py
theus/delta.py
theus/engine.py
theus/guards.py
theus/interfaces.py
theus/linter.py
theus/locks.py
theus/orchestrator/__init__.py
theus/orchestrator/bus.py
theus/orchestrator/executor.py
theus/orchestrator/fsm.py
theus/orchestrator/manager.py
theus/parallel.py
theus/scaffold/main.py
theus/scaffold/requirements.txt
theus/scaffold/specs/audit_ecommerce.yaml
theus/scaffold/specs/audit_recipe.yaml
theus/scaffold/specs/context_schema.yaml
theus/scaffold/specs/workflow.yaml
theus/scaffold/src/context.py
theus/scaffold/src/processes/async_outbox.py
theus/scaffold/src/processes/ecommerce.py
theus/scaffold/src/processes/parallel.py
theus/scaffold/workflows/async_outbox.yaml
theus/scaffold/workflows/ecommerce.yaml
theus/schema_gen.py
theus/structures.py
theus/workflow.py
theus/zones.py
theus-3.0.21.dist-info/METADATA
theus-3.0.21.dist-info/WHEEL
theus-3.0.21.dist-info/entry_points.txt
theus-3.0.21.dist-info/licenses/LICENSE
theus_core/__init__.py
theus_core/theus_core.abi3.so
theus-3.0.21.dist-info/RECORD
