Metadata-Version: 2.4
Name: theus
Version: 3.0.21
Classifier: Development Status :: 5 - Production/Stable
Classifier: Intended Audience :: Developers
Classifier: Intended Audience :: Science/Research
Classifier: Programming Language :: Rust
Classifier: Programming Language :: Python :: 3
Classifier: Programming Language :: Python :: 3.12
Classifier: Programming Language :: Python :: 3.13
Classifier: Programming Language :: Python :: 3.14
Classifier: License :: OSI Approved :: MIT License
Classifier: Operating System :: OS Independent
Classifier: Topic :: Software Development :: Libraries :: Application Frameworks
Classifier: Topic :: Scientific/Engineering :: Artificial Intelligence
Classifier: Topic :: System :: Monitoring
Requires-Dist: pydantic>=2.0
Requires-Dist: pyyaml>=6.0
Requires-Dist: typing-extensions>=4.0
Requires-Dist: rich>=13.0
Requires-Dist: questionary>=2.0
License-File: LICENSE
Summary: Reliable, Rust-Powered Agentic AI Framework with Transactional Memory.
Keywords: ai,agents,rust,memory,transactional,safety,pop,framework
Author-email: Do Huy Hoang <dohuyhoangvn93@gmail.com>
Requires-Python: >=3.12
Project-URL: Homepage, https://github.com/dohuyhoang93/theus
Project-URL: Issues, https://github.com/dohuyhoang93/theus/issues
Project-URL: Repository, https://github.com/dohuyhoang93/theus
